discord-stubs/__init__.pyi
discord-stubs/__main__.pyi
discord-stubs/_types.pyi
discord-stubs/abc.pyi
discord-stubs/activity.pyi
discord-stubs/appinfo.pyi
discord-stubs/asset.pyi
discord-stubs/audit_logs.pyi
discord-stubs/automod.pyi
discord-stubs/backoff.pyi
discord-stubs/channel.pyi
discord-stubs/client.pyi
discord-stubs/colour.pyi
discord-stubs/components.pyi
discord-stubs/context_managers.pyi
discord-stubs/embeds.pyi
discord-stubs/emoji.pyi
discord-stubs/enums.pyi
discord-stubs/errors.pyi
discord-stubs/file.pyi
discord-stubs/flags.pyi
discord-stubs/gateway.pyi
discord-stubs/guild.pyi
discord-stubs/http.pyi
discord-stubs/integrations.pyi
discord-stubs/interactions.pyi
discord-stubs/invite.pyi
discord-stubs/member.pyi
discord-stubs/mentions.pyi
discord-stubs/message.pyi
discord-stubs/mixins.pyi
discord-stubs/object.pyi
discord-stubs/oggparse.pyi
discord-stubs/opus.pyi
discord-stubs/partial_emoji.pyi
discord-stubs/permissions.pyi
discord-stubs/player.pyi
discord-stubs/raw_models.pyi
discord-stubs/reaction.pyi
discord-stubs/role.pyi
discord-stubs/scheduled_event.pyi
discord-stubs/shard.pyi
discord-stubs/stage_instance.pyi
discord-stubs/state.pyi
discord-stubs/sticker.pyi
discord-stubs/team.pyi
discord-stubs/template.pyi
discord-stubs/threads.pyi
discord-stubs/user.pyi
discord-stubs/utils.pyi
discord-stubs/voice_client.pyi
discord-stubs/welcome_screen.pyi
discord-stubs/widget.pyi
discord-stubs/app_commands/__init__.pyi
discord-stubs/app_commands/checks.pyi
discord-stubs/app_commands/commands.pyi
discord-stubs/app_commands/errors.pyi
discord-stubs/app_commands/models.pyi
discord-stubs/app_commands/namespace.pyi
discord-stubs/app_commands/transformers.pyi
discord-stubs/app_commands/translator.pyi
discord-stubs/app_commands/tree.pyi
discord-stubs/ext/commands/__init__.pyi
discord-stubs/ext/commands/_types.pyi
discord-stubs/ext/commands/bot.pyi
discord-stubs/ext/commands/cog.pyi
discord-stubs/ext/commands/context.pyi
discord-stubs/ext/commands/converter.pyi
discord.py_listen_overloads-2.3.2.dist-info/LICENSE
discord.py_listen_overloads-2.3.2.dist-info/METADATA
discord.py_listen_overloads-2.3.2.dist-info/WHEEL
discord.py_listen_overloads-2.3.2.dist-info/top_level.txt
discord.py_listen_overloads-2.3.2.dist-info/RECORD
