Metadata-Version: 2.1
Name: discord.py-listen-overloads
Version: 2.3.2
Summary: A stubs package for discord.py that adds overloads to the commands.Bot.listen decorator.
Author: Soheab_
License: Mozilla Public License Version 2.0
Project-URL: homepage, https://github.com/Soheab/discord.py-listen-overloads
Project-URL: repository, https://github.com/Soheab/discord.py-listen-overloads
Keywords: discord.py,dpy,discord,events,stubs,overloads,listen
Classifier: Development Status :: 5 - Production/Stable
Classifier: Intended Audience :: Developers
Classifier: Typing :: Typed
Requires-Python: >=3.8
License-File: LICENSE
Requires-Dist: discord.py <3.0.0,>=2.0.0
